lambdashim/__init__.py
lambdashim/typing.py
lambdashim/wsgi.py
lambdashim-0.1.0.dist-info/WHEEL
lambdashim-0.1.0.dist-info/METADATA
lambdashim-0.1.0.dist-info/RECORD
