Metadata-Version: 2.1
Name: lambdashim
Version: 0.1.0
Summary: A little wsgi shim for AWS Lambda.
Author: Abram Isola
Author-email: abram@isola.mn
Requires-Python: >=3.7,<4.0
Classifier: Programming Language :: Python :: 3
Classifier: Programming Language :: Python :: 3.10
Classifier: Programming Language :: Python :: 3.7
Classifier: Programming Language :: Python :: 3.8
Classifier: Programming Language :: Python :: 3.9
